iatorch/__init__.py
iatorch/app.py
iatorch/data.py
iatorch/models.py
iatorch/trainers.py
iatorch/audio/__init__.py
iatorch/audio/transforms.py
iatorch/audio/utils.py
iatorch/config/__init__.py
iatorch/config/availables.py
iatorch/config/parameters.py
iatorch/db/__init__.py
iatorch/db/utils.py
iatorch/db/experiments/__init__.py
iatorch/db/experiments/migrations/__init__.py
iatorch/db/experiments/migrations/env.py
iatorch/db/migrations/__init__.py
iatorch/db/migrations/alembic.ini
iatorch/db/migrations/env.py
iatorch/db/project/__init__.py
iatorch/db/project/model.py
iatorch/db/project/migrations/__init__.py
iatorch/db/project/migrations/env.py
iatorch/lightning/__init__.py
iatorch/lightning/data.py
iatorch/lightning/models.py
iatorch/lightning/transforms.py
iatorch/lightning/utils.py
iatorch/loggers/__init__.py
iatorch/loggers/mlflow.py
iatorch/scripts/__init__.py
iatorch/scripts/project.py
iatorch/scripts/train.py
iatorch/utils/__init__.py
iatorch/utils/parser.py
iatorch/utils/process.py
iatorch/utils/utils.py
iatorch/vision/__init__.py
iatorch-0.3.16.dist-info/METADATA
iatorch-0.3.16.dist-info/WHEEL
iatorch-0.3.16.dist-info/entry_points.txt
iatorch-0.3.16.dist-info/top_level.txt
iatorch-0.3.16.dist-info/RECORD
