Metadata-Version: 2.1
Name: iatorch
Version: 0.3.16
Summary: PyTorch Wrapper for Inspection AI
Home-page: http://mod.lge.com/hub/smartdata/iatorch
Author: Woojin Cho
Author-email: lg.woojin.cho@lge.com
License: UNKNOWN
Download-URL: http://mod.lge.com/hub/smartdata/iatorch/archive/0.3.16.tar.gz
Keywords: pytorch,pytorch-lightning
Platform: UNKNOWN
Classifier: Programming Language :: Python :: 3
Classifier: Programming Language :: Python :: 3.7
Classifier: Programming Language :: Python :: 3.8
Requires-Python: >=3
Requires-Dist: click (>=7.0)
Requires-Dist: pandas (>=1.2)
Requires-Dist: future (>=0.17.1)
Requires-Dist: PyYAML (>=5.1)
Requires-Dist: tqdm (>=4.41.0)
Requires-Dist: torch (>=1.4)
Requires-Dist: torchvision (>=0.7)
Requires-Dist: pytorch-lightning (>=1.1.6)
Requires-Dist: tensorboard (>=2.2)
Requires-Dist: mlflow (>=1.13)
Requires-Dist: librosa (>=0.8.0)
Requires-Dist: opencv-python (>=3.4.2)
Requires-Dist: nptdms (>=0.27.0)
Requires-Dist: pysftp (==0.2.8)
Requires-Dist: paramiko (==2.7.1)
Requires-Dist: efficientnet-pytorch (>=0.7.0)
Requires-Dist: iautils (>=0.3.8)
Requires-Dist: dirsync (>=2.2.5)
